{"name":"org/moddingx/libx/datagen/provider/texture/TextureBuilder","simpleName":"TextureBuilder","sourceName":"org.moddingx.libx.datagen.provider.texture.TextureBuilder","modifiers":["public"],"superClass":{"name":"java/lang/Object","signature":"java.lang.Object","parameters":[]},"constructors":[{"modifiers":["public"],"typeId":"(org.moddingx.libx.mod.ModX,java.util.function.Function<net.minecraft.resources.ResourceLocation,java.awt.image.BufferedImage>)void","parameters":[{"name":"mod","type":{"name":"org.moddingx.libx.mod.ModX","desc":"Lorg/moddingx/libx/mod/ModX;","binaryName":"org/moddingx/libx/mod/ModX"}},{"name":"textureLoader","type":{"name":"java.util.function.Function<net.minecraft.resources.ResourceLocation,java.awt.image.BufferedImage>","desc":"Ljava/util/function/Function;","binaryName":"java/util/function/Function"}}],"return":{"name":"void","desc":"V"}}],"methods":[{"name":"addTexture","modifiers":["public"],"typeId":"(java.lang.String,int)org.moddingx.libx.datagen.provider.texture.TextureBuilder","parameters":[{"name":"loc","type":{"name":"java.lang.String","desc":"Ljava/lang/String;","binaryName":"java/lang/String"}},{"name":"defaultSize","type":{"name":"int","desc":"I"}}],"return":{"name":"org.moddingx.libx.datagen.provider.texture.TextureBuilder","desc":"Lorg/moddingx/libx/datagen/provider/texture/TextureBuilder;","binaryName":"org/moddingx/libx/datagen/provider/texture/TextureBuilder"},"doc":{"summary":"Adds a required texture which has the given size by default as width and height.","text":"Adds a required texture which has the given size by default as width and height."}},{"name":"addImage","modifiers":["public"],"typeId":"(java.lang.String,int)org.moddingx.libx.datagen.provider.texture.TextureBuilder","parameters":[{"name":"loc","type":{"name":"java.lang.String","desc":"Ljava/lang/String;","binaryName":"java/lang/String"}},{"name":"defaultSize","type":{"name":"int","desc":"I"}}],"return":{"name":"org.moddingx.libx.datagen.provider.texture.TextureBuilder","desc":"Lorg/moddingx/libx/datagen/provider/texture/TextureBuilder;","binaryName":"org/moddingx/libx/datagen/provider/texture/TextureBuilder"},"doc":{"summary":"Adds a required image which has the given size by default as width and height.","text":"Adds a required image which has the given size by default as width and height."}},{"name":"addTexture","modifiers":["public"],"typeId":"(net.minecraft.resources.ResourceLocation,int)org.moddingx.libx.datagen.provider.texture.TextureBuilder","parameters":[{"name":"loc","type":{"name":"net.minecraft.resources.ResourceLocation","desc":"Lnet/minecraft/resources/ResourceLocation;","binaryName":"net/minecraft/resources/ResourceLocation"}},{"name":"defaultSize","type":{"name":"int","desc":"I"}}],"return":{"name":"org.moddingx.libx.datagen.provider.texture.TextureBuilder","desc":"Lorg/moddingx/libx/datagen/provider/texture/TextureBuilder;","binaryName":"org/moddingx/libx/datagen/provider/texture/TextureBuilder"},"doc":{"summary":"Adds a required texture which has the given size by default as width and height.","text":"Adds a required texture which has the given size by default as width and height."}},{"name":"addImage","modifiers":["public"],"typeId":"(net.minecraft.resources.ResourceLocation,int)org.moddingx.libx.datagen.provider.texture.TextureBuilder","parameters":[{"name":"loc","type":{"name":"net.minecraft.resources.ResourceLocation","desc":"Lnet/minecraft/resources/ResourceLocation;","binaryName":"net/minecraft/resources/ResourceLocation"}},{"name":"defaultSize","type":{"name":"int","desc":"I"}}],"return":{"name":"org.moddingx.libx.datagen.provider.texture.TextureBuilder","desc":"Lorg/moddingx/libx/datagen/provider/texture/TextureBuilder;","binaryName":"org/moddingx/libx/datagen/provider/texture/TextureBuilder"},"doc":{"summary":"Adds a required image which has the given size by default as width and height.","text":"Adds a required image which has the given size by default as width and height."}},{"name":"addTexture","modifiers":["public"],"typeId":"(java.lang.String,int,int)org.moddingx.libx.datagen.provider.texture.TextureBuilder","parameters":[{"name":"loc","type":{"name":"java.lang.String","desc":"Ljava/lang/String;","binaryName":"java/lang/String"}},{"name":"defaultWidth","type":{"name":"int","desc":"I"}},{"name":"defaultHeight","type":{"name":"int","desc":"I"}}],"return":{"name":"org.moddingx.libx.datagen.provider.texture.TextureBuilder","desc":"Lorg/moddingx/libx/datagen/provider/texture/TextureBuilder;","binaryName":"org/moddingx/libx/datagen/provider/texture/TextureBuilder"},"doc":{"summary":"Adds a required texture which has the given width and height by default.","text":"Adds a required texture which has the given width and height by default."}},{"name":"addImage","modifiers":["public"],"typeId":"(java.lang.String,int,int)org.moddingx.libx.datagen.provider.texture.TextureBuilder","parameters":[{"name":"loc","type":{"name":"java.lang.String","desc":"Ljava/lang/String;","binaryName":"java/lang/String"}},{"name":"defaultWidth","type":{"name":"int","desc":"I"}},{"name":"defaultHeight","type":{"name":"int","desc":"I"}}],"return":{"name":"org.moddingx.libx.datagen.provider.texture.TextureBuilder","desc":"Lorg/moddingx/libx/datagen/provider/texture/TextureBuilder;","binaryName":"org/moddingx/libx/datagen/provider/texture/TextureBuilder"},"doc":{"summary":"Adds a required image which has the given width and height by default.","text":"Adds a required image which has the given width and height by default."}},{"name":"addTexture","modifiers":["public"],"typeId":"(net.minecraft.resources.ResourceLocation,int,int)org.moddingx.libx.datagen.provider.texture.TextureBuilder","parameters":[{"name":"loc","type":{"name":"net.minecraft.resources.ResourceLocation","desc":"Lnet/minecraft/resources/ResourceLocation;","binaryName":"net/minecraft/resources/ResourceLocation"}},{"name":"defaultWidth","type":{"name":"int","desc":"I"}},{"name":"defaultHeight","type":{"name":"int","desc":"I"}}],"return":{"name":"org.moddingx.libx.datagen.provider.texture.TextureBuilder","desc":"Lorg/moddingx/libx/datagen/provider/texture/TextureBuilder;","binaryName":"org/moddingx/libx/datagen/provider/texture/TextureBuilder"},"doc":{"summary":"Adds a required texture which has the given width and height by default.","text":"Adds a required texture which has the given width and height by default."}},{"name":"addFake","modifiers":["public"],"typeId":"(net.minecraft.resources.ResourceLocation,java.awt.image.BufferedImage)org.moddingx.libx.datagen.provider.texture.TextureBuilder","parameters":[{"name":"loc","type":{"name":"net.minecraft.resources.ResourceLocation","desc":"Lnet/minecraft/resources/ResourceLocation;","binaryName":"net/minecraft/resources/ResourceLocation"},"doc":"A fake <i>image</i> id."},{"name":"image","type":{"name":"java.awt.image.BufferedImage","desc":"Ljava/awt/image/BufferedImage;","binaryName":"java/awt/image/BufferedImage"}}],"return":{"name":"org.moddingx.libx.datagen.provider.texture.TextureBuilder","desc":"Lorg/moddingx/libx/datagen/provider/texture/TextureBuilder;","binaryName":"org/moddingx/libx/datagen/provider/texture/TextureBuilder"},"doc":{"summary":"Assigns the given id to a fake image.","text":"Assigns the given id to a fake image."}},{"name":"addFake","modifiers":["public"],"typeId":"(net.minecraft.resources.ResourceLocation,java.awt.image.BufferedImage,int)org.moddingx.libx.datagen.provider.texture.TextureBuilder","parameters":[{"name":"loc","type":{"name":"net.minecraft.resources.ResourceLocation","desc":"Lnet/minecraft/resources/ResourceLocation;","binaryName":"net/minecraft/resources/ResourceLocation"},"doc":"A fake <i>image</i> id."},{"name":"image","type":{"name":"java.awt.image.BufferedImage","desc":"Ljava/awt/image/BufferedImage;","binaryName":"java/awt/image/BufferedImage"}},{"name":"scale","type":{"name":"int","desc":"I"}}],"return":{"name":"org.moddingx.libx.datagen.provider.texture.TextureBuilder","desc":"Lorg/moddingx/libx/datagen/provider/texture/TextureBuilder;","binaryName":"org/moddingx/libx/datagen/provider/texture/TextureBuilder"},"doc":{"summary":"Assigns the given id to a fake image and scale.","text":"Assigns the given id to a fake image and scale."}},{"name":"addFakeTexture","modifiers":["public"],"typeId":"(net.minecraft.resources.ResourceLocation,net.minecraft.resources.ResourceLocation,java.util.function.UnaryOperator<java.awt.image.BufferedImage>)org.moddingx.libx.datagen.provider.texture.TextureBuilder","parameters":[{"name":"loc","type":{"name":"net.minecraft.resources.ResourceLocation","desc":"Lnet/minecraft/resources/ResourceLocation;","binaryName":"net/minecraft/resources/ResourceLocation"},"doc":"A fake <i>image</i> id."},{"name":"texLoc","type":{"name":"net.minecraft.resources.ResourceLocation","desc":"Lnet/minecraft/resources/ResourceLocation;","binaryName":"net/minecraft/resources/ResourceLocation"}},{"name":"image","type":{"name":"java.util.function.UnaryOperator<java.awt.image.BufferedImage>","desc":"Ljava/util/function/UnaryOperator;","binaryName":"java/util/function/UnaryOperator"}}],"return":{"name":"org.moddingx.libx.datagen.provider.texture.TextureBuilder","desc":"Lorg/moddingx/libx/datagen/provider/texture/TextureBuilder;","binaryName":"org/moddingx/libx/datagen/provider/texture/TextureBuilder"},"doc":{"summary":"Assigns the given id to a fake image that is obtained by transforming another image.","text":"Assigns the given id to a fake image that is obtained by transforming another image.  This requires that the texture <code>texLoc</code> has already been added."}},{"name":"addFakeImage","modifiers":["public"],"typeId":"(net.minecraft.resources.ResourceLocation,net.minecraft.resources.ResourceLocation,java.util.function.UnaryOperator<java.awt.image.BufferedImage>)org.moddingx.libx.datagen.provider.texture.TextureBuilder","parameters":[{"name":"loc","type":{"name":"net.minecraft.resources.ResourceLocation","desc":"Lnet/minecraft/resources/ResourceLocation;","binaryName":"net/minecraft/resources/ResourceLocation"},"doc":"A fake <i>image</i> id."},{"name":"imgLoc","type":{"name":"net.minecraft.resources.ResourceLocation","desc":"Lnet/minecraft/resources/ResourceLocation;","binaryName":"net/minecraft/resources/ResourceLocation"}},{"name":"image","type":{"name":"java.util.function.UnaryOperator<java.awt.image.BufferedImage>","desc":"Ljava/util/function/UnaryOperator;","binaryName":"java/util/function/UnaryOperator"}}],"return":{"name":"org.moddingx.libx.datagen.provider.texture.TextureBuilder","desc":"Lorg/moddingx/libx/datagen/provider/texture/TextureBuilder;","binaryName":"org/moddingx/libx/datagen/provider/texture/TextureBuilder"},"doc":{"summary":"Assigns the given id to a fake image that is obtained by transforming another image.","text":"Assigns the given id to a fake image that is obtained by transforming another image.  This requires that the image <code>imgLoc</code> has already been added."}},{"name":"addImage","modifiers":["public"],"typeId":"(net.minecraft.resources.ResourceLocation,int,int)org.moddingx.libx.datagen.provider.texture.TextureBuilder","parameters":[{"name":"loc","type":{"name":"net.minecraft.resources.ResourceLocation","desc":"Lnet/minecraft/resources/ResourceLocation;","binaryName":"net/minecraft/resources/ResourceLocation"}},{"name":"defaultWidth","type":{"name":"int","desc":"I"}},{"name":"defaultHeight","type":{"name":"int","desc":"I"}}],"return":{"name":"org.moddingx.libx.datagen.provider.texture.TextureBuilder","desc":"Lorg/moddingx/libx/datagen/provider/texture/TextureBuilder;","binaryName":"org/moddingx/libx/datagen/provider/texture/TextureBuilder"},"doc":{"summary":"Adds a required image which has the given width and height by default.","text":"Adds a required image which has the given width and height by default."}},{"name":"build","modifiers":["public"],"typeId":"()org.moddingx.libx.datagen.provider.texture.Textures","parameters":[],"return":{"name":"org.moddingx.libx.datagen.provider.texture.Textures","desc":"Lorg/moddingx/libx/datagen/provider/texture/Textures;","binaryName":"org/moddingx/libx/datagen/provider/texture/Textures"},"doc":{"summary":"Creates the resulting <ref cls=\"org/moddingx/libx/datagen/provider/texture/Textures\">Textures</ref> object.","text":"Creates the resulting <ref cls=\"org/moddingx/libx/datagen/provider/texture/Textures\">Textures</ref> object."}}],"doc":{"summary":"A texture builder is used to preload required textures to build another texture and compute  scales for the source textures and the target texture.","text":"A texture builder is used to preload required textures to build another texture and compute  scales for the source textures and the target texture. It is used to build a <ref cls=\"org/moddingx/libx/datagen/provider/texture/Textures\">Textures</ref>  object.<br>   See <ref cls=\"org/moddingx/libx/datagen/provider/texture/TextureProviderBase\">TextureProviderBase</ref> for the difference between <i>image</i> and <i>texture</i> ids  and for information on scaling."}}
