{"name":"org/moddingx/libx/util/data/TagAccess","simpleName":"TagAccess","sourceName":"org.moddingx.libx.util.data.TagAccess","modifiers":["public"],"superClass":{"name":"java/lang/Object","signature":"java.lang.Object","parameters":[]},"methods":[{"name":"create","modifiers":["public","static"],"typeId":"(net.minecraft.core.RegistryAccess)org.moddingx.libx.util.data.TagAccess","parameters":[{"name":"registries","type":{"name":"net.minecraft.core.RegistryAccess","desc":"Lnet/minecraft/core/RegistryAccess;","binaryName":"net/minecraft/core/RegistryAccess"}}],"return":{"name":"org.moddingx.libx.util.data.TagAccess","desc":"Lorg/moddingx/libx/util/data/TagAccess;","binaryName":"org/moddingx/libx/util/data/TagAccess"},"doc":{"summary":"Creates a new <ref cls=\"org/moddingx/libx/util/data/TagAccess\">TagAccess</ref> from a given <ref cls=\"net/minecraft/core/RegistryAccess\">RegistryAccess</ref>.","text":"Creates a new <ref cls=\"org/moddingx/libx/util/data/TagAccess\">TagAccess</ref> from a given <ref cls=\"net/minecraft/core/RegistryAccess\">RegistryAccess</ref>."}},{"name":"create","modifiers":["public","static"],"typeId":"(net.minecraft.server.MinecraftServer)org.moddingx.libx.util.data.TagAccess","parameters":[{"name":"server","type":{"name":"net.minecraft.server.MinecraftServer","desc":"Lnet/minecraft/server/MinecraftServer;","binaryName":"net/minecraft/server/MinecraftServer"}}],"return":{"name":"org.moddingx.libx.util.data.TagAccess","desc":"Lorg/moddingx/libx/util/data/TagAccess;","binaryName":"org/moddingx/libx/util/data/TagAccess"},"doc":{"summary":"Creates a new <ref cls=\"org/moddingx/libx/util/data/TagAccess\">TagAccess</ref> for a given <ref cls=\"net/minecraft/server/MinecraftServer\">MinecraftServer</ref>.","text":"Creates a new <ref cls=\"org/moddingx/libx/util/data/TagAccess\">TagAccess</ref> for a given <ref cls=\"net/minecraft/server/MinecraftServer\">MinecraftServer</ref>."}},{"name":"create","modifiers":["public","static"],"typeId":"(net.minecraft.world.level.Level)org.moddingx.libx.util.data.TagAccess","parameters":[{"name":"level","type":{"name":"net.minecraft.world.level.Level","desc":"Lnet/minecraft/world/level/Level;","binaryName":"net/minecraft/world/level/Level"}}],"return":{"name":"org.moddingx.libx.util.data.TagAccess","desc":"Lorg/moddingx/libx/util/data/TagAccess;","binaryName":"org/moddingx/libx/util/data/TagAccess"},"doc":{"summary":"Creates a new <ref cls=\"org/moddingx/libx/util/data/TagAccess\">TagAccess</ref> for a given <ref cls=\"net/minecraft/world/level/Level\">Level</ref>.","text":"Creates a new <ref cls=\"org/moddingx/libx/util/data/TagAccess\">TagAccess</ref> for a given <ref cls=\"net/minecraft/world/level/Level\">Level</ref>."}},{"name":"get","modifiers":["public"],"typeId":"<T>(net.minecraft.tags.TagKey<T>)net.minecraft.core.HolderSet.Named<T>","parameters":[{"name":"key","type":{"name":"net.minecraft.tags.TagKey<T>","desc":"Lnet/minecraft/tags/TagKey;","binaryName":"net/minecraft/tags/TagKey"}}],"return":{"name":"net.minecraft.core.HolderSet.Named<T>","desc":"Lnet/minecraft/core/HolderSet$Named;","binaryName":"net/minecraft/core/HolderSet$Named"},"doc":{"summary":"Gets the <ref cls=\"net/minecraft/core/HolderSet\">HolderSet</ref> associated with a tag.","text":"Gets the <ref cls=\"net/minecraft/core/HolderSet\">HolderSet</ref> associated with a tag.  If the tag does not yet exist, it is created."}},{"name":"tryGet","modifiers":["public"],"typeId":"<T>(net.minecraft.tags.TagKey<T>)java.util.Optional<net.minecraft.core.HolderSet.Named<T>>","parameters":[{"name":"key","type":{"name":"net.minecraft.tags.TagKey<T>","desc":"Lnet/minecraft/tags/TagKey;","binaryName":"net/minecraft/tags/TagKey"}}],"return":{"name":"java.util.Optional<net.minecraft.core.HolderSet.Named<T>>","desc":"Ljava/util/Optional;","binaryName":"java/util/Optional"},"doc":{"summary":"Gets the <ref cls=\"net/minecraft/core/HolderSet\">HolderSet</ref> associated with a tag.","text":"Gets the <ref cls=\"net/minecraft/core/HolderSet\">HolderSet</ref> associated with a tag.  If the tag does not yet exist, the returned <ref cls=\"java/util/Optional\">Optional</ref> will be empty."}},{"name":"has","modifiers":["public"],"typeId":"<T>(net.minecraft.tags.TagKey<T>,T)boolean","parameters":[{"name":"key","type":{"name":"net.minecraft.tags.TagKey<T>","desc":"Lnet/minecraft/tags/TagKey;","binaryName":"net/minecraft/tags/TagKey"}},{"name":"value","type":{"name":"T","typeVar":"T"}}],"return":{"name":"boolean","desc":"Z"},"doc":{"summary":"Checks whether a tag has a certain element.","text":"Checks whether a tag has a certain element."}},{"name":"random","modifiers":["public"],"typeId":"<T>(net.minecraft.tags.TagKey<T>,net.minecraft.util.RandomSource)java.util.Optional<T>","parameters":[{"name":"key","type":{"name":"net.minecraft.tags.TagKey<T>","desc":"Lnet/minecraft/tags/TagKey;","binaryName":"net/minecraft/tags/TagKey"}},{"name":"random","type":{"name":"net.minecraft.util.RandomSource","desc":"Lnet/minecraft/util/RandomSource;","binaryName":"net/minecraft/util/RandomSource"}}],"return":{"name":"java.util.Optional<T>","desc":"Ljava/util/Optional;","binaryName":"java/util/Optional"},"doc":{"summary":"Gets a random element from a tag.","text":"Gets a random element from a tag."}}],"doc":{"summary":"A class to help accessing <ref cls=\"net/minecraft/tags/TagKey\">tags</ref> in a more user friendly way.","text":"A class to help accessing <ref cls=\"net/minecraft/tags/TagKey\">tags</ref> in a more user friendly way.  A <ref cls=\"org/moddingx/libx/util/data/TagAccess\">TagAccess</ref> can contain a <ref cls=\"net/minecraft/core/RegistryAccess\">RegistryAccess</ref> to allow accessing  dynamic registries.","properties":[{"text":"Use <ref cls=\"net/minecraft/core/HolderSet\">HolderSet</ref>s where possible in datapack registries and <ref cls=\"net/minecraftforge/registries/tags/ITagManager\">ITagManager</ref> for              forge non-datapack registries.","type":"deprecated"}]}}
